sphinxmermaid/__init__.py
sphinx_mermaid-0.0.8.dist-info/METADATA
sphinx_mermaid-0.0.8.dist-info/WHEEL
sphinx_mermaid-0.0.8.dist-info/top_level.txt
sphinx_mermaid-0.0.8.dist-info/RECORD
